fyers_token_manager_3/__init__.py
fyers_token_manager_3/base_token_manager.py
fyers_token_manager_3-0.1.2.dist-info/LICENSE
fyers_token_manager_3-0.1.2.dist-info/METADATA
fyers_token_manager_3-0.1.2.dist-info/WHEEL
fyers_token_manager_3-0.1.2.dist-info/RECORD
