Metadata-Version: 2.1
Name: fyers-token-manager-3
Version: 0.1.2
Summary: 
Author: Krunal Dodiya
Author-email: kunal.dodiya1@gmail.com
Requires-Python: >=3.10,<4.0
Classifier: Programming Language :: Python :: 3
Classifier: Programming Language :: Python :: 3.10
Classifier: Programming Language :: Python :: 3.11
Classifier: Programming Language :: Python :: 3.12
Requires-Dist: fyers-apiv3 (>=3.0.7,<4.0.0)
Requires-Dist: logzero (>=1.7.0,<2.0.0)
Requires-Dist: pyotp (>=2.9.0,<3.0.0)
Requires-Dist: requests (>=2.31.0,<3.0.0)
Requires-Dist: websockets (>=12.0,<13.0)
